docker_rerun.py
docker_rerun-0.1.1.dist-info/DESCRIPTION.rst
docker_rerun-0.1.1.dist-info/METADATA
docker_rerun-0.1.1.dist-info/RECORD
docker_rerun-0.1.1.dist-info/WHEEL
docker_rerun-0.1.1.dist-info/entry_points.txt
docker_rerun-0.1.1.dist-info/metadata.json
docker_rerun-0.1.1.dist-info/top_level.txt
