Metadata-Version: 2.0
Name: docker-rerun
Version: 0.1.1
Summary: Command-line tool to re-run a docker container
Home-page: https://github.com/csmith/docker-rerun
Author: Chris Smith
Author-email: chris87@gmail.com
License: MIT
Keywords: docker container
Platform: UNKNOWN
Classifier: Development Status :: 4 - Beta
Classifier: Intended Audience :: Developers
Classifier: Intended Audience :: System Administrators
Classifier: License :: OSI Approved :: MIT License
Classifier: Programming Language :: Python :: 3 :: Only
Classifier: Topic :: System :: Systems Administration
Classifier: Topic :: Utilities
Provides-Extra: dev
Provides-Extra: test
Requires-Dist: coverage; extra == 'test'
Requires-Dist: nose; extra == 'test'
Requires-Dist: pylint; extra == 'test'
